masim/__init__.py
masim/cli.py
masim/foo.py
masim-0.1.0.dist-info/METADATA
masim-0.1.0.dist-info/WHEEL
masim-0.1.0.dist-info/entry_points.txt
masim-0.1.0.dist-info/top_level.txt
masim-0.1.0.dist-info/RECORD
