Metadata-Version: 2.4
Name: masim
Version: 0.1.0
Summary: multi-agent simulation
Project-URL: Repository, https://github.com/time-integral/masim
Requires-Python: >=3.11
Requires-Dist: click>=8.2.0
